[{"Dataset": "trump", "Dataset Size": 44252, "Model": "NMF", "Params": {"num_topics": 10, "random_state": 21}, "Scores": {"npmi": -0.003917059704810471, "diversity": 0.46}, "Computation Time": 37.59049582481384}, {"Dataset": "trump", "Dataset Size": 44252, "Model": "NMF", "Params": {"num_topics": 20, "random_state": 21}, "Scores": {"npmi": 0.007975363716605934, "diversity": 0.415}, "Computation Time": 57.661266565322876}, {"Dataset": "trump", "Dataset Size": 44252, "Model": "NMF", "Params": {"num_topics": 30, "random_state": 21}, "Scores": {"npmi": 0.02100240700031533, "diversity": 0.38}, "Computation Time": 90.17007565498352}, {"Dataset": "trump", "Dataset Size": 44252, "Model": "NMF", "Params": {"num_topics": 40, "random_state": 21}, "Scores": {"npmi": 0.010374395636827632, "diversity": 0.36}, "Computation Time": 123.77262783050537}, {"Dataset": "trump", "Dataset Size": 44252, "Model": "NMF", "Params": {"num_topics": 50, "random_state": 21}, "Scores": {"npmi": 0.006939519775300629, "diversity": 0.316}, "Computation Time": 150.9620659351349}]